smoothy/__init__.py
smoothy/core/__init__.py
smoothy/core/analysis.py
smoothy/core/utilities.py
smoothy/io/__init__.py
smoothy/io/fits.py
smoothy/io/graph.py
smoothy/upi/__init__.py
smoothy/upi/axes.py
smoothy/upi/data.py
smoothy/upi/flux.py
smoothy/upi/formatting.py
smoothy/upi/reduction.py
smoothy-0.1.0.dist-info/DESCRIPTION.rst
smoothy-0.1.0.dist-info/METADATA
smoothy-0.1.0.dist-info/RECORD
smoothy-0.1.0.dist-info/WHEEL
smoothy-0.1.0.dist-info/metadata.json
smoothy-0.1.0.dist-info/top_level.txt
