Metadata-Version: 2.0
Name: smoothy
Version: 0.1.0
Summary: Package that provides an easy interface and I/O operations for using astronomical libraries.
Home-page: https://github.com/ChileanVirtualObservatory/smoothy
Author: CSRG
Author-email: contact@lirae.cl
License: UNKNOWN
Platform: UNKNOWN
Classifier: Intended Audience :: Science/Research
Classifier: Topic :: Scientific/Engineering :: Astronomy
Classifier: Programming Language :: Python :: 2.7
Classifier: Programming Language :: Python :: 3.6
Requires-Dist: astropy (>=1.2)
Requires-Dist: matplotlib (>=1.5)
Requires-Dist: numpy (>=1.11.2)
